mqttxx/__init__.py
mqttxx/client.py
mqttxx/config.py
mqttxx/events.py
mqttxx/exceptions.py
mqttxx/properties.py
mqttxx/protocol.py
mqttxx/rpc.py
mqttxx-4.0.3.dist-info/LICENSE
mqttxx-4.0.3.dist-info/METADATA
mqttxx-4.0.3.dist-info/WHEEL
mqttxx-4.0.3.dist-info/top_level.txt
mqttxx-4.0.3.dist-info/RECORD
