Metadata-Version: 2.1
Name: mqttxx
Version: 4.0.3
Summary: 基于 aiomqtt 的高级 MQTT 客户端和 RPC 框架
Author: MQTTX Team
License: MIT
Keywords: mqtt,rpc,async,iot,messaging
License-File: LICENSE
Requires-Dist: aiomqtt <3.0.0,>=2.0.0
Requires-Dist: loguru >=0.7.0
Provides-Extra: dev
Requires-Dist: pytest ; extra == 'dev'
Requires-Dist: pytest-asyncio ; extra == 'dev'
Requires-Dist: pytest-rich ; extra == 'dev'
Requires-Dist: pydantic ; extra == 'dev'
Requires-Dist: ruff ; extra == 'dev'
Requires-Dist: build ; extra == 'dev'
Requires-Dist: twine ; extra == 'dev'
